LICENSE
MANIFEST.in
README.md
setup.cfg
setup.py
ethercalc/__init__.py
ethercalc_python.egg-info/PKG-INFO
ethercalc_python.egg-info/SOURCES.txt
ethercalc_python.egg-info/dependency_links.txt
ethercalc_python.egg-info/requires.txt
ethercalc_python.egg-info/top_level.txt
examples/dumpsheet.py
examples/hello.py
examples/loadsheet.py
examples/test_export.py