Metadata-Version: 1.0
Name: ethercalc-python
Version: 0.0.4
Summary: A python API to ethercalc
Home-page: https://github.com/joequant/ethercalc-python
Author: Joseph C Wang
Author-email: joequant@gmail.com
License: BSD
Platform: UNKNOWN
